iceaddr/__init__.py
iceaddr/addresses.py
iceaddr/db.py
iceaddr/geo.py
iceaddr/iceaddr.db
iceaddr/meta.py
iceaddr/municipalities.py
iceaddr/nearest.py
iceaddr/placenames.py
iceaddr/postcodes.py
iceaddr-0.6.1.dist-info/licenses/LICENSE.txt
iceaddr-0.6.1.dist-info/METADATA
iceaddr-0.6.1.dist-info/WHEEL
iceaddr-0.6.1.dist-info/top_level.txt
iceaddr-0.6.1.dist-info/RECORD
