Metadata-Version: 2.4
Name: iceaddr
Version: 0.6.1
Summary: Look up information about Icelandic street addresses, postcodes, landmarks, locations and placenames
Author-email: Sveinbjorn Thordarson <sveinbjorn@sveinbjorn.org>
Maintainer-email: Sveinbjorn Thordarson <sveinbjorn@sveinbjorn.org>
License-Expression: BSD-3-Clause
Project-URL: Repository, https://github.com/sveinbjornt/iceaddr
Project-URL: Documentation, https://github.com/sveinbjornt/iceaddr#readme
Project-URL: Issues, https://github.com/sveinbjornt/iceaddr/issues
Project-URL: Changelog, https://github.com/sveinbjornt/iceaddr#version-history
Keywords: addresses,postcodes,placenames,landmarks,locations,iceland,icelandic,geocoding,geopositioning
Classifier: Operating System :: OS Independent
Classifier: Development Status :: 5 - Production/Stable
Classifier: Intended Audience :: Developers
Classifier: Natural Language :: Icelandic
Classifier: Programming Language :: Python
Classifier: Programming Language :: Python :: 3
Classifier: Programming Language :: Python :: 3 :: Only
Classifier: Programming Language :: Python :: 3.9
Classifier: Programming Language :: Python :: 3.10
Classifier: Programming Language :: Python :: 3.11
Classifier: Programming Language :: Python :: 3.12
Classifier: Programming Language :: Python :: 3.13
Classifier: Programming Language :: Python :: 3.14
Classifier: Topic :: Software Development :: Libraries :: Python Modules
Classifier: Topic :: Utilities
Classifier: Topic :: Text Processing :: Linguistic
Requires-Python: >=3.9
License-File: LICENSE.txt
Provides-Extra: dev
Requires-Dist: pytest>=8.4.2; extra == "dev"
Requires-Dist: types-setuptools>=68.2.0; extra == "dev"
Requires-Dist: ruff>=0.12.17; extra == "dev"
Requires-Dist: pyright>=1.1.0; extra == "dev"
Requires-Dist: coverage[toml]>=7.3.1; extra == "dev"
Requires-Dist: requests>=2.26.0; extra == "dev"
Provides-Extra: build
Requires-Dist: fiona>=1.9.4; extra == "build"
Requires-Dist: humanize>=0.5.1; extra == "build"
Requires-Dist: reynir>=3.1.0; extra == "build"
Dynamic: license-file
